tordoc
