Metadata-Version: 1.0
Name: tordoc
Version: 0.0.1
Summary: generate api doc and online debug
Home-page: UNKNOWN
Author: tuxpy
Author-email: UNKNOWN
License: UNKNOWN
Platform: UNKNOWN
